ddopnew/__init__.py
ddopnew/_modidx.py
ddopnew/core.py
ddopnew/utils.py
ddopnew/envs/__init__.py
ddopnew/envs/inventory.py
ddopnew-0.0.2.dist-info/LICENSE
ddopnew-0.0.2.dist-info/METADATA
ddopnew-0.0.2.dist-info/WHEEL
ddopnew-0.0.2.dist-info/entry_points.txt
ddopnew-0.0.2.dist-info/top_level.txt
ddopnew-0.0.2.dist-info/RECORD
