Metadata-Version: 2.1
Name: ddopnew
Version: 0.0.2
Summary: A completely new version of ddop. New name to be specificed.
Home-page: https://github.com/opimwue/ddopnew
Author: kaiguender
Author-email: kai.guender@yahoo.de
License: Apache Software License 2.0
Keywords: nbdev jupyter notebook python
Classifier: Development Status :: 4 - Beta
Classifier: Intended Audience :: Developers
Classifier: Natural Language :: English
Classifier: Programming Language :: Python :: 3.7
Classifier: Programming Language :: Python :: 3.8
Classifier: Programming Language :: Python :: 3.9
Classifier: Programming Language :: Python :: 3.10
Classifier: License :: OSI Approved :: Apache Software License
Requires-Python: >=3.7
License-File: LICENSE
Provides-Extra: dev
